ksef_client/__init__.py
ksef_client/client.py
ksef_client/config.py
ksef_client/exceptions.py
ksef_client/http.py
ksef_client/models.py
ksef_client/openapi_models.py
ksef_client/py.typed
ksef_client/types.py
ksef_client/clients/__init__.py
ksef_client/clients/auth.py
ksef_client/clients/base.py
ksef_client/clients/certificates.py
ksef_client/clients/invoices.py
ksef_client/clients/limits.py
ksef_client/clients/peppol.py
ksef_client/clients/permissions.py
ksef_client/clients/rate_limits.py
ksef_client/clients/security.py
ksef_client/clients/sessions.py
ksef_client/clients/testdata.py
ksef_client/clients/tokens.py
ksef_client/services/__init__.py
ksef_client/services/auth.py
ksef_client/services/batch.py
ksef_client/services/crypto.py
ksef_client/services/csr.py
ksef_client/services/hwm.py
ksef_client/services/person_token.py
ksef_client/services/qr.py
ksef_client/services/verification_link.py
ksef_client/services/workflows.py
ksef_client/services/xades.py
ksef_client/utils/__init__.py
ksef_client/utils/base64url.py
ksef_client/utils/ksef_number.py
ksef_client/utils/zip_utils.py
ksef_client-0.3.1.dist-info/licenses/LICENSE
ksef_client-0.3.1.dist-info/METADATA
ksef_client-0.3.1.dist-info/WHEEL
ksef_client-0.3.1.dist-info/top_level.txt
ksef_client-0.3.1.dist-info/RECORD
