Metadata-Version: 2.4
Name: ksef-client
Version: 0.3.1
Summary: Client SDK for KSeF API v2
Author-email: "Mateusz Smektała (smekcio)" <mateusz@smkc.dev>
License-Expression: MIT
Project-URL: Repository, https://github.com/smekcio/ksef-client-python
Project-URL: Documentation, https://github.com/smekcio/ksef-client-python/blob/main/docs/README.md
Project-URL: Issues, https://github.com/smekcio/ksef-client-python/issues
Keywords: ksef,e-invoice,poland,api
Classifier: Programming Language :: Python :: 3
Classifier: Operating System :: OS Independent
Requires-Python: >=3.10
License-File: LICENSE
Requires-Dist: httpx>=0.27.0
Requires-Dist: cryptography>=42.0.0
Provides-Extra: xml
Requires-Dist: lxml>=5.0.0; extra == "xml"
Requires-Dist: xmlsec>=1.3.13; extra == "xml"
Provides-Extra: qr
Requires-Dist: qrcode[pil]>=7.4.2; extra == "qr"
Requires-Dist: pillow>=10.0.0; extra == "qr"
Dynamic: license-file
